{
    "Ac": {
        "filename": "Ac.us.z_11.ld1.psl.v1.0.0-high.upf",
        "total_psenergy": -93.63782261,
        "pseudopotential": "100US",
        "relativistic": "scalar",
        "cutoff_wfc": 40,
        "cutoff_rho": 320,
        "valence_electrons": 11.00,
        "total_magnetization": -0.01,
        "absolute_magnetization": 0.01,
        "md5": ""
    },
    "Ag": {
        "filename": "Ag_ONCV_PBEsol-1.0.upf",
        "total_psenergy": -286.99651969,
        "pseudopotential": "SG15",
        "relativistic": "scalar",
        "cutoff_wfc": 55,
        "cutoff_rho": 220,
        "valence_electrons": 19.00,
        "total_magnetization": -0.00,
        "absolute_magnetization": 0.00,
        "md5": ""
    },
    "Al": {
        "filename": "Al.pbesol-n-kjpaw_psl.1.0.0.UPF",
        "total_psenergy": -38.21239231,
        "pseudopotential": "100PAW",
        "relativistic": "scalar",
        "cutoff_wfc": 30,
        "cutoff_rho": 240,
        "valence_electrons": 3.00,
        "total_magnetization": 0.00,
        "absolute_magnetization": 0.01,
        "md5": ""
    },
    "Am": {
        "filename": "Am.paw.z_17.ld1.uni-marburg.v0.upf",
        "total_psenergy": -1124.97557705,
        "pseudopotential": "MalteSachs",
        "relativistic": "scalar",
        "cutoff_wfc": 60,
        "cutoff_rho": 480,
        "valence_electrons": 17.00,
        "total_magnetization": 1.00,
        "absolute_magnetization": 2.89,
        "md5": ""
    },
    "Ar": {
        "filename": "Ar.paw.z_8.ld1.psl.v1.0.0-high.upf",
        "total_psenergy": -93.55116398,
        "pseudopotential": "100PAW",
        "relativistic": "scalar",
        "cutoff_wfc": 120,
        "cutoff_rho": 960,
        "valence_electrons": 8.00,
        "total_magnetization": 0.00,
        "absolute_magnetization": 0.00,
        "md5": ""
    },
    "As": {
        "filename": "As.nc.z_15.oncvpsp3.dojo.v4-std.upf",
        "total_psenergy": -211.45200931,
        "pseudopotential": "Dojo",
        "relativistic": "scalar",
        "cutoff_wfc": 75,
        "cutoff_rho": 300,
        "valence_electrons": 15.00,
        "total_magnetization": -0.00,
        "absolute_magnetization": 0.00,
        "md5": ""
    },
    "At": {
        "filename": "At.us.z_17.ld1.psl.v1.0.0-high.upf",
        "total_psenergy": -220.00683896,
        "pseudopotential": "100US",
        "relativistic": "scalar",
        "cutoff_wfc": 80,
        "cutoff_rho": 640,
        "valence_electrons": 17.00,
        "total_magnetization": -0.01,
        "absolute_magnetization": 0.01,
        "md5": ""
    },
    "Au": {
        "filename": "Au_ONCV_PBEsol-1.0.upf",
        "total_psenergy": -274.46179533,
        "pseudopotential": "SG15",
        "relativistic": "scalar",
        "cutoff_wfc": 50,
        "cutoff_rho": 200,
        "valence_electrons": 19.00,
        "total_magnetization": 0.01,
        "absolute_magnetization": 0.01,
        "md5": ""
    },
    "Ba": {
        "filename": "Ba.nc.z_10.oncvpsp4.dojo.v4-sp.upf",
        "total_psenergy": -55.98961109,
        "pseudopotential": "Dojo",
        "relativistic": "scalar",
        "cutoff_wfc": 35,
        "cutoff_rho": 140,
        "valence_electrons": 10.00,
        "total_magnetization": 0.00,
        "absolute_magnetization": 0.00,
        "md5": ""
    },
    "Be": {
        "filename": "Be_ONCV_PBEsol-1.0.upf",
        "total_psenergy": -26.15838450,
        "pseudopotential": "SG15",
        "relativistic": "scalar",
        "cutoff_wfc": 55,
        "cutoff_rho": 220,
        "valence_electrons": 4.00,
        "total_magnetization": -0.00,
        "absolute_magnetization": 0.00,
        "md5": ""
    },
    "Bi": {
        "filename": "bi_pbesol_v1.uspp.F.UPF",
        "total_psenergy": -184.65579012,
        "pseudopotential": "GBRV-1.2",
        "relativistic": "scalar",
        "cutoff_wfc": 50,
        "cutoff_rho": 400,
        "valence_electrons": 15.00,
        "total_magnetization": 0.00,
        "absolute_magnetization": 0.01,
        "md5": ""
    },
    "Bk": {
        "filename": "Bk.paw.z_19.ld1.uni-marburg.v0.upf",
        "total_psenergy": -1211.72203571,
        "pseudopotential": "MalteSachs",
        "relativistic": "scalar",
        "cutoff_wfc": 60,
        "cutoff_rho": 480,
        "valence_electrons": 19.00,
        "total_magnetization": 0.01,
        "absolute_magnetization": 2.17,
        "md5": ""
    },
    "B": {
        "filename": "b_pbesol_v1.4.uspp.F.UPF",
        "total_psenergy": -5.83807726,
        "pseudopotential": "GBRV-1.2",
        "relativistic": "scalar",
        "cutoff_wfc": 55,
        "cutoff_rho": 440,
        "valence_electrons": 3.00,
        "total_magnetization": 0.01,
        "absolute_magnetization": 0.01,
        "md5": ""
    },
    "Br": {
        "filename": "br_pbesol_v1.4.uspp.F.UPF",
        "total_psenergy": -40.37688196,
        "pseudopotential": "GBRV-1.4",
        "relativistic": "scalar",
        "cutoff_wfc": 90,
        "cutoff_rho": 720,
        "valence_electrons": 7.00,
        "total_magnetization": 0.00,
        "absolute_magnetization": 0.00,
        "md5": ""
    },
    "Ca": {
        "filename": "ca_pbesol_v1.uspp.F.UPF",
        "total_psenergy": -74.77659498,
        "pseudopotential": "GBRV-1.2",
        "relativistic": "scalar",
        "cutoff_wfc": 30,
        "cutoff_rho": 240,
        "valence_electrons": 10.00,
        "total_magnetization": -0.00,
        "absolute_magnetization": 0.00,
        "md5": ""
    },
    "Cd": {
        "filename": "Cd.paw.z_20.ld1.psl.v1.0.0-high.upf",
        "total_psenergy": -600.88057595,
        "pseudopotential": "100PAW",
        "relativistic": "scalar",
        "cutoff_wfc": 100,
        "cutoff_rho": 800,
        "valence_electrons": 20.00,
        "total_magnetization": 0.00,
        "absolute_magnetization": 0.00,
        "md5": ""
    },
    "Ce": {
        "filename": "Ce.paw.z_12.atompaw.wentzcovitch.v1.2.upf",
        "total_psenergy": -475.04654098,
        "pseudopotential": "Wentzcovitch",
        "relativistic": "scalar",
        "cutoff_wfc": 50,
        "cutoff_rho": 400,
        "valence_electrons": 12.00,
        "total_magnetization": -0.57,
        "absolute_magnetization": 1.50,
        "md5": ""
    },
    "Cf": {
        "filename": "Cf.paw.z_20.ld1.uni-marburg.v0.upf",
        "total_psenergy": -1259.43522956,
        "pseudopotential": "MalteSachs",
        "relativistic": "scalar",
        "cutoff_wfc": 60,
        "cutoff_rho": 480,
        "valence_electrons": 20.00,
        "total_magnetization": -0.01,
        "absolute_magnetization": 2.10,
        "md5": ""
    },
    "Cl": {
        "filename": "Cl.pbesol-n-rrkjus_psl.1.0.0.UPF",
        "total_psenergy": -34.34536867,
        "pseudopotential": "100US",
        "relativistic": "scalar",
        "cutoff_wfc": 100,
        "cutoff_rho": 800,
        "valence_electrons": 7.00,
        "total_magnetization": -0.00,
        "absolute_magnetization": 0.00,
        "md5": ""
    },
    "Cm": {
        "filename": "Cm.paw.z_18.ld1.uni-marburg.v0.upf",
        "total_psenergy": -4342.98482590,
        "pseudopotential": "MalteSachs",
        "relativistic": "scalar",
        "cutoff_wfc": 60,
        "cutoff_rho": 480,
        "valence_electrons": 18.00,
        "total_magnetization": 0.00,
        "absolute_magnetization": 0.00,
        "md5": ""
    },
    "Co": {
        "filename": "co_pbesol_v1.2.uspp.F.UPF",
        "total_psenergy": -297.78642698,
        "pseudopotential": "GBRV-1.2",
        "relativistic": "scalar",
        "cutoff_wfc": 90,
        "cutoff_rho": 1080,
        "valence_electrons": 17.00,
        "total_magnetization": 0.97,
        "absolute_magnetization": 2.02,
        "md5": ""
    },
    "C": {
        "filename": "C.pbesol-n-kjpaw_psl.1.0.0.UPF",
        "total_psenergy": -17.41243718,
        "pseudopotential": "100PAW",
        "relativistic": "scalar",
        "cutoff_wfc": 45,
        "cutoff_rho": 360,
        "valence_electrons": 4.00,
        "total_magnetization": 0.01,
        "absolute_magnetization": 0.01,
        "md5": ""
    },
    "Cr": {
        "filename": "cr_pbesol_v1.5.uspp.F.UPF",
        "total_psenergy": -175.07389141,
        "pseudopotential": "GBRV-1.5",
        "relativistic": "scalar",
        "cutoff_wfc": 40,
        "cutoff_rho": 320,
        "valence_electrons": 14.00,
        "total_magnetization": 6.00,
        "absolute_magnetization": 6.00,
        "md5": ""
    },
    "Cs": {
        "filename": "Cs.nc.z_9.oncvpsp3.dojo.v4-str.upf",
        "total_psenergy": -46.53659833,
        "pseudopotential": "Dojo",
        "relativistic": "scalar",
        "cutoff_wfc": 45,
        "cutoff_rho": 180,
        "valence_electrons": 9.00,
        "total_magnetization": -0.00,
        "absolute_magnetization": 0.00,
        "md5": ""
    },
    "Cu": {
        "filename": "Cu.paw.z_11.ld1.psl.v1.0.0-low.upf",
        "total_psenergy": -210.13279691,
        "pseudopotential": "100PAW-low",
        "relativistic": "scalar",
        "cutoff_wfc": 90,
        "cutoff_rho": 720,
        "valence_electrons": 11.00,
        "total_magnetization": -1.00,
        "absolute_magnetization": 1.10,
        "md5": ""
    },
    "Dy": {
        "filename": "Dy.paw.z_20.atompaw.wentzcovitch.v1.2.upf",
        "total_psenergy": -769.00154875,
        "pseudopotential": "Wentzcovitch",
        "relativistic": "scalar",
        "cutoff_wfc": 40,
        "cutoff_rho": 320,
        "valence_electrons": 20.00,
        "total_magnetization": -0.00,
        "absolute_magnetization": 1.01,
        "md5": ""
    },
    "Er": {
        "filename": "Er.paw.z_22.atompaw.wentzcovitch.v1.2.upf",
        "total_psenergy": -877.43816466,
        "pseudopotential": "Wentzcovitch",
        "relativistic": "scalar",
        "cutoff_wfc": 40,
        "cutoff_rho": 320,
        "valence_electrons": 22.00,
        "total_magnetization": 0.04,
        "absolute_magnetization": 0.60,
        "md5": ""
    },
    "Es": {
        "filename": "Es.paw.z_21.ld1.uni-marburg.v0.upf",
        "total_psenergy": -1310.18847995,
        "pseudopotential": "MalteSachs",
        "relativistic": "scalar",
        "cutoff_wfc": 60,
        "cutoff_rho": 480,
        "valence_electrons": 21.00,
        "total_magnetization": -1.19,
        "absolute_magnetization": 1.98,
        "md5": ""
    },
    "Eu": {
        "filename": "Eu.paw.z_17.atompaw.wentzcovitch.v1.2.upf",
        "total_psenergy": -863.25494290,
        "pseudopotential": "Wentzcovitch",
        "relativistic": "scalar",
        "cutoff_wfc": 40,
        "cutoff_rho": 320,
        "valence_electrons": 17.00,
        "total_magnetization": 1.00,
        "absolute_magnetization": 1.30,
        "md5": ""
    },
    "Fe": {
        "filename": "Fe.pbesol-spn-kjpaw_psl.0.2.1.UPF",
        "total_psenergy": -326.52359112,
        "pseudopotential": "031PAW",
        "relativistic": "scalar",
        "cutoff_wfc": 90,
        "cutoff_rho": 1080,
        "valence_electrons": 16.00,
        "total_magnetization": -4.00,
        "absolute_magnetization": 4.01,
        "md5": ""
    },
    "Fm": {
        "filename": "Fm.paw.z_22.ld1.uni-marburg.v0.upf",
        "total_psenergy": -1364.12717941,
        "pseudopotential": "MalteSachs",
        "relativistic": "scalar",
        "cutoff_wfc": 60,
        "cutoff_rho": 480,
        "valence_electrons": 22.00,
        "total_magnetization": 2.05,
        "absolute_magnetization": 2.05,
        "md5": ""
    },
    "F": {
        "filename": "F.oncvpsp.upf",
        "total_psenergy": -48.80655407,
        "pseudopotential": "Dojo",
        "relativistic": "scalar",
        "cutoff_wfc": 90,
        "cutoff_rho": 360,
        "valence_electrons": 7.00,
        "total_magnetization": 0.00,
        "absolute_magnetization": 0.00,
        "md5": ""
    },
    "Fr": {
        "filename": "Fr.paw.z_19.ld1.psl.v1.0.0-high.upf",
        "total_psenergy": -1059.38032125,
        "pseudopotential": "100PAW",
        "relativistic": "scalar",
        "cutoff_wfc": 150,
        "cutoff_rho": 1200,
        "valence_electrons": 19.00,
        "total_magnetization": 0.01,
        "absolute_magnetization": 0.01,
        "md5": ""
    },
    "Ga": {
        "filename": "Ga.pbesol-dn-kjpaw_psl.1.0.0.UPF",
        "total_psenergy": -274.76237275,
        "pseudopotential": "100PAW",
        "relativistic": "scalar",
        "cutoff_wfc": 90,
        "cutoff_rho": 720,
        "valence_electrons": 13.00,
        "total_magnetization": 0.01,
        "absolute_magnetization": 0.01,
        "md5": ""
    },
    "Gd": {
        "filename": "Gd.paw.z_18.atompaw.wentzcovitch.v1.2.upf",
        "total_psenergy": -675.81551183,
        "pseudopotential": "Wentzcovitch",
        "relativistic": "scalar",
        "cutoff_wfc": 40,
        "cutoff_rho": 320,
        "valence_electrons": 18.00,
        "total_magnetization": 0.00,
        "absolute_magnetization": 0.76,
        "md5": ""
    },
    "Ge": {
        "filename": "ge_pbesol_v1.4.uspp.F.UPF",
        "total_psenergy": -212.82254129,
        "pseudopotential": "GBRV-1.4",
        "relativistic": "scalar",
        "cutoff_wfc": 45,
        "cutoff_rho": 360,
        "valence_electrons": 14.00,
        "total_magnetization": 0.00,
        "absolute_magnetization": 0.00,
        "md5": ""
    },
    "He": {
        "filename": "He_ONCV_PBEsol-1.0.upf",
        "total_psenergy": -5.51625750,
        "pseudopotential": "SG15",
        "relativistic": "scalar",
        "cutoff_wfc": 55,
        "cutoff_rho": 220,
        "valence_electrons": 2.00,
        "total_magnetization": 0.00,
        "absolute_magnetization": 0.00,
        "md5": ""
    },
    "Hf": {
        "filename": "Hf-sp.oncvpsp.upf",
        "total_psenergy": -112.25944296,
        "pseudopotential": "Dojo",
        "relativistic": "scalar",
        "cutoff_wfc": 55,
        "cutoff_rho": 220,
        "valence_electrons": 12.00,
        "total_magnetization": -0.00,
        "absolute_magnetization": 0.00,
        "md5": ""
    },
    "Hg": {
        "filename": "Hg.us.z_12.uspp.gbrv.v1.upf",
        "total_psenergy": -107.49401317,
        "pseudopotential": "GBRV-v1.0",
        "relativistic": "scalar",
        "cutoff_wfc": 65,
        "cutoff_rho": 390,
        "valence_electrons": 12.00,
        "total_magnetization": 0.00,
        "absolute_magnetization": 0.00,
        "md5": ""
    },
    "H": {
        "filename": "H_ONCV_PBEsol-1.0.upf",
        "total_psenergy": -0.90394874,
        "pseudopotential": "SG15",
        "relativistic": "scalar",
        "cutoff_wfc": 80,
        "cutoff_rho": 320,
        "valence_electrons": 1.00,
        "total_magnetization": 0.00,
        "absolute_magnetization": 0.00,
        "md5": ""
    },
    "Ho": {
        "filename": "Ho.paw.z_21.atompaw.wentzcovitch.v1.2.upf",
        "total_psenergy": -821.23024650,
        "pseudopotential": "Wentzcovitch",
        "relativistic": "scalar",
        "cutoff_wfc": 40,
        "cutoff_rho": 320,
        "valence_electrons": 21.00,
        "total_magnetization": 0.00,
        "absolute_magnetization": 0.79,
        "md5": ""
    },
    "I": {
        "filename": "I.nc.z_17.oncvpsp4.sg15.v0.upf",
        "total_psenergy": -198.63684623,
        "pseudopotential": "SG15",
        "relativistic": "scalar",
        "cutoff_wfc": 65,
        "cutoff_rho": 260,
        "valence_electrons": 17.00,
        "total_magnetization": 0.02,
        "absolute_magnetization": 0.02,
        "md5": ""
    },
    "In": {
        "filename": "In.pbesol-dn-rrkjus_psl.0.2.2.UPF",
        "total_psenergy": -144.18048787,
        "pseudopotential": "031US",
        "relativistic": "scalar",
        "cutoff_wfc": 50,
        "cutoff_rho": 400,
        "valence_electrons": 13.00,
        "total_magnetization": -0.01,
        "absolute_magnetization": 0.01,
        "md5": ""
    },
    "Ir": {
        "filename": "Ir.us.z_31.ld1.psl.v1.0.0-high.upf",
        "total_psenergy": -963.43030206,
        "pseudopotential": "100US",
        "relativistic": "scalar",
        "cutoff_wfc": 90,
        "cutoff_rho": 720,
        "valence_electrons": 31.00,
        "total_magnetization": -1.13,
        "absolute_magnetization": 2.30,
        "md5": ""
    },
    "K": {
        "filename": "K.pbesol-spn-kjpaw_psl.1.0.0.UPF",
        "total_psenergy": -111.36990577,
        "pseudopotential": "100PAW",
        "relativistic": "scalar",
        "cutoff_wfc": 60,
        "cutoff_rho": 480,
        "valence_electrons": 9.00,
        "total_magnetization": -0.00,
        "absolute_magnetization": 0.00,
        "md5": ""
    },
    "Kr": {
        "filename": "Kr.paw.z_18.ld1.psl.v1.0.0-high.upf",
        "total_psenergy": -500.72278497,
        "pseudopotential": "100PAW",
        "relativistic": "scalar",
        "cutoff_wfc": 200,
        "cutoff_rho": 1200,
        "valence_electrons": 18.00,
        "total_magnetization": 0.00,
        "absolute_magnetization": 0.00,
        "md5": ""
    },
    "La": {
        "filename": "La.paw.z_11.atompaw.wentzcovitch.v1.2.upf",
        "total_psenergy": -451.42225396,
        "pseudopotential": "Wentzcovitch",
        "relativistic": "scalar",
        "cutoff_wfc": 40,
        "cutoff_rho": 320,
        "valence_electrons": 11.00,
        "total_magnetization": -1.03,
        "absolute_magnetization": 1.77,
        "md5": ""
    },
    "Li": {
        "filename": "li_pbesol_v1.4.uspp.F.UPF",
        "total_psenergy": -14.27312204,
        "pseudopotential": "GBRV-1.4",
        "relativistic": "scalar",
        "cutoff_wfc": 40,
        "cutoff_rho": 320,
        "valence_electrons": 3.00,
        "total_magnetization": 0.04,
        "absolute_magnetization": 0.04,
        "md5": ""
    },
    "Lr": {
        "filename": "Lr.paw.z_25.ld1.uni-marburg.v0.upf",
        "total_psenergy": -1545.29828507,
        "pseudopotential": "MalteSachs",
        "relativistic": "scalar",
        "cutoff_wfc": 60,
        "cutoff_rho": 480,
        "valence_electrons": 25.00,
        "total_magnetization": 0.01,
        "absolute_magnetization": 0.01,
        "md5": ""
    },
    "Lu": {
        "filename": "Lu.paw.z_25.atompaw.wentzcovitch.v1.2.upf",
        "total_psenergy": -1071.07216645,
        "pseudopotential": "Wentzcovitch",
        "relativistic": "scalar",
        "cutoff_wfc": 45,
        "cutoff_rho": 360,
        "valence_electrons": 25.00,
        "total_magnetization": 0.00,
        "absolute_magnetization": 0.01,
        "md5": ""
    },
    "Md": {
        "filename": "Md.paw.z_23.ld1.uni-marburg.v0.upf",
        "total_psenergy": -1421.31157970,
        "pseudopotential": "MalteSachs",
        "relativistic": "scalar",
        "cutoff_wfc": 60,
        "cutoff_rho": 480,
        "valence_electrons": 23.00,
        "total_magnetization": -1.04,
        "absolute_magnetization": 1.05,
        "md5": ""
    },
    "Mg": {
        "filename": "mg_pbesol_v1.4.uspp.F.UPF",
        "total_psenergy": -125.02578886,
        "pseudopotential": "GBRV-1.4",
        "relativistic": "scalar",
        "cutoff_wfc": 45,
        "cutoff_rho": 360,
        "valence_electrons": 10.00,
        "total_magnetization": -0.00,
        "absolute_magnetization": 0.00,
        "md5": ""
    },
    "Mn": {
        "filename": "mn_pbesol_v1.5.uspp.F.UPF",
        "total_psenergy": -210.78348652,
        "pseudopotential": "GBRV-1.5",
        "relativistic": "scalar",
        "cutoff_wfc": 90,
        "cutoff_rho": 1080,
        "valence_electrons": 15.00,
        "total_magnetization": 5.00,
        "absolute_magnetization": 5.17,
        "md5": ""
    },
    "Mo": {
        "filename": "Mo_ONCV_PBEsol-1.0.upf",
        "total_psenergy": -136.49494286,
        "pseudopotential": "SG15",
        "relativistic": "scalar",
        "cutoff_wfc": 35,
        "cutoff_rho": 140,
        "valence_electrons": 14.00,
        "total_magnetization": -1.96,
        "absolute_magnetization": 3.61,
        "md5": ""
    },
    "Na": {
        "filename": "Na.paw.z_9.ld1.psl.v1.0.0-low.upf",
        "total_psenergy": -108.41288689,
        "pseudopotential": "100PAW-low",
        "relativistic": "scalar",
        "cutoff_wfc": 100,
        "cutoff_rho": 800,
        "valence_electrons": 9.00,
        "total_magnetization": -0.01,
        "absolute_magnetization": 0.01,
        "md5": ""
    },
    "Nb": {
        "filename": "Nb.pbesol-spn-kjpaw_psl.0.3.0.UPF",
        "total_psenergy": -329.42726820,
        "pseudopotential": "031PAW",
        "relativistic": "scalar",
        "cutoff_wfc": 40,
        "cutoff_rho": 320,
        "valence_electrons": 13.00,
        "total_magnetization": 0.99,
        "absolute_magnetization": 2.83,
        "md5": ""
    },
    "Nd": {
        "filename": "Nd.paw.z_14.atompaw.wentzcovitch.v1.2.upf",
        "total_psenergy": -530.20444284,
        "pseudopotential": "Wentzcovitch",
        "relativistic": "scalar",
        "cutoff_wfc": 40,
        "cutoff_rho": 320,
        "valence_electrons": 14.00,
        "total_magnetization": -4.00,
        "absolute_magnetization": 4.06,
        "md5": ""
    },
    "Ne": {
        "filename": "Ne.paw.z_8.ld1.psl.v1.0.0-high.upf",
        "total_psenergy": -81.32716668,
        "pseudopotential": "100PAW",
        "relativistic": "scalar",
        "cutoff_wfc": 120,
        "cutoff_rho": 720,
        "valence_electrons": 8.00,
        "total_magnetization": -0.00,
        "absolute_magnetization": 0.00,
        "md5": ""
    },
    "Ni": {
        "filename": "ni_pbesol_v1.4.uspp.F.UPF",
        "total_psenergy": -342.67940541,
        "pseudopotential": "GBRV-1.4",
        "relativistic": "scalar",
        "cutoff_wfc": 50,
        "cutoff_rho": 400,
        "valence_electrons": 18.00,
        "total_magnetization": -0.56,
        "absolute_magnetization": 1.55,
        "md5": ""
    },
    "N": {
        "filename": "N.oncvpsp.upf",
        "total_psenergy": -20.04705582,
        "pseudopotential": "Dojo",
        "relativistic": "scalar",
        "cutoff_wfc": 80,
        "cutoff_rho": 320,
        "valence_electrons": 5.00,
        "total_magnetization": 0.00,
        "absolute_magnetization": 0.00,
        "md5": ""
    },
    "No": {
        "filename": "No.paw.z_24.ld1.uni-marburg.v0.upf",
        "total_psenergy": -1481.90631898,
        "pseudopotential": "MalteSachs",
        "relativistic": "scalar",
        "cutoff_wfc": 60,
        "cutoff_rho": 480,
        "valence_electrons": 24.00,
        "total_magnetization": -0.00,
        "absolute_magnetization": 0.00,
        "md5": ""
    },
    "Np": {
        "filename": "Np.paw.z_15.ld1.uni-marburg.v0.upf",
        "total_psenergy": -1048.83865774,
        "pseudopotential": "MalteSachs",
        "relativistic": "scalar",
        "cutoff_wfc": 60,
        "cutoff_rho": 480,
        "valence_electrons": 15.00,
        "total_magnetization": 0.96,
        "absolute_magnetization": 2.83,
        "md5": ""
    },
    "O": {
        "filename": "O.pbesol-n-kjpaw_psl.0.1.UPF",
        "total_psenergy": -40.64209049,
        "pseudopotential": "031PAW",
        "relativistic": "scalar",
        "cutoff_wfc": 75,
        "cutoff_rho": 600,
        "valence_electrons": 6.00,
        "total_magnetization": 0.00,
        "absolute_magnetization": 0.00,
        "md5": ""
    },
    "Os": {
        "filename": "os_pbesol_v1.2.uspp.F.UPF",
        "total_psenergy": -197.81067883,
        "pseudopotential": "GBRV-1.2",
        "relativistic": "scalar",
        "cutoff_wfc": 40,
        "cutoff_rho": 320,
        "valence_electrons": 16.00,
        "total_magnetization": 0.84,
        "absolute_magnetization": 2.63,
        "md5": ""
    },
    "Pa": {
        "filename": "Pa.paw.z_13.ld1.uni-marburg.v0.upf",
        "total_psenergy": -982.53324184,
        "pseudopotential": "MalteSachs",
        "relativistic": "scalar",
        "cutoff_wfc": 60,
        "cutoff_rho": 480,
        "valence_electrons": 13.00,
        "total_magnetization": 3.00,
        "absolute_magnetization": 3.35,
        "md5": ""
    },
    "Pb": {
        "filename": "Pb.pbesol-dn-kjpaw_psl.0.2.2.UPF",
        "total_psenergy": -859.12381671,
        "pseudopotential": "031PAW",
        "relativistic": "scalar",
        "cutoff_wfc": 45,
        "cutoff_rho": 360,
        "valence_electrons": 14.00,
        "total_magnetization": -0.01,
        "absolute_magnetization": 0.01,
        "md5": ""
    },
    "Pd": {
        "filename": "Pd_ONCV_PBEsol-1.0.upf",
        "total_psenergy": -252.79691276,
        "pseudopotential": "SG15",
        "relativistic": "scalar",
        "cutoff_wfc": 50,
        "cutoff_rho": 200,
        "valence_electrons": 18.00,
        "total_magnetization": 0.00,
        "absolute_magnetization": 0.11,
        "md5": ""
    },
    "Pm": {
        "filename": "Pm.paw.z_15.atompaw.wentzcovitch.v1.2.upf",
        "total_psenergy": -561.81004953,
        "pseudopotential": "Wentzcovitch",
        "relativistic": "scalar",
        "cutoff_wfc": 40,
        "cutoff_rho": 320,
        "valence_electrons": 15.00,
        "total_magnetization": 0.08,
        "absolute_magnetization": 1.18,
        "md5": ""
    },
    "Po": {
        "filename": "Po.pbesol-dn-rrkjus_psl.1.0.0.UPF",
        "total_psenergy": -194.99621262,
        "pseudopotential": "100US",
        "relativistic": "scalar",
        "cutoff_wfc": 80,
        "cutoff_rho": 640,
        "valence_electrons": 16.00,
        "total_magnetization": 0.00,
        "absolute_magnetization": 0.01,
        "md5": ""
    },
    "P": {
        "filename": "P.pbesol-n-rrkjus_psl.1.0.0.UPF",
        "total_psenergy": -13.62037482,
        "pseudopotential": "100US",
        "relativistic": "scalar",
        "cutoff_wfc": 30,
        "cutoff_rho": 240,
        "valence_electrons": 5.00,
        "total_magnetization": -0.01,
        "absolute_magnetization": 0.01,
        "md5": ""
    },
    "Pr": {
        "filename": "Pr.paw.z_13.atompaw.wentzcovitch.v1.2.upf",
        "total_psenergy": -501.20773901,
        "pseudopotential": "Wentzcovitch",
        "relativistic": "scalar",
        "cutoff_wfc": 40,
        "cutoff_rho": 320,
        "valence_electrons": 13.00,
        "total_magnetization": -0.28,
        "absolute_magnetization": 1.47,
        "md5": ""
    },
    "Pt": {
        "filename": "Pt.pbesol-spfn-rrkjus_psl.1.0.0.UPF",
        "total_psenergy": -1032.41255707,
        "pseudopotential": "100US",
        "relativistic": "scalar",
        "cutoff_wfc": 100,
        "cutoff_rho": 800,
        "valence_electrons": 32.00,
        "total_magnetization": 1.33,
        "absolute_magnetization": 1.67,
        "md5": ""
    },
    "Pu": {
        "filename": "Pu.paw.z_16.ld1.uni-marburg.v0.upf",
        "total_psenergy": -1085.82969094,
        "pseudopotential": "MalteSachs",
        "relativistic": "scalar",
        "cutoff_wfc": 60,
        "cutoff_rho": 480,
        "valence_electrons": 16.00,
        "total_magnetization": 6.00,
        "absolute_magnetization": 6.25,
        "md5": ""
    },
    "Ra": {
        "filename": "Ra.paw.z_20.ld1.psl.v1.0.0-high.upf",
        "total_psenergy": -1105.94462346,
        "pseudopotential": "100PAW",
        "relativistic": "scalar",
        "cutoff_wfc": 90,
        "cutoff_rho": 720,
        "valence_electrons": 20.00,
        "total_magnetization": 0.00,
        "absolute_magnetization": 0.00,
        "md5": ""
    },
    "Rb": {
        "filename": "Rb_ONCV_PBEsol-1.0.upf",
        "total_psenergy": -48.91876431,
        "pseudopotential": "SG15",
        "relativistic": "scalar",
        "cutoff_wfc": 30,
        "cutoff_rho": 120,
        "valence_electrons": 9.00,
        "total_magnetization": -0.00,
        "absolute_magnetization": 0.00,
        "md5": ""
    },
    "Re": {
        "filename": "re_pbesol_v1.2.uspp.F.UPF",
        "total_psenergy": -189.60098452,
        "pseudopotential": "GBRV-1.2",
        "relativistic": "scalar",
        "cutoff_wfc": 30,
        "cutoff_rho": 240,
        "valence_electrons": 15.00,
        "total_magnetization": 0.99,
        "absolute_magnetization": 2.90,
        "md5": ""
    },
    "Rh": {
        "filename": "Rh_ONCV_PBEsol-1.0.upf",
        "total_psenergy": -216.39618058,
        "pseudopotential": "SG15",
        "relativistic": "scalar",
        "cutoff_wfc": 55,
        "cutoff_rho": 220,
        "valence_electrons": 17.00,
        "total_magnetization": 0.00,
        "absolute_magnetization": 1.53,
        "md5": ""
    },
    "Rn": {
        "filename": "Rn.paw.z_18.ld1.psl.v1.0.0-high.upf",
        "total_psenergy": -1015.02204268,
        "pseudopotential": "100PAW",
        "relativistic": "scalar",
        "cutoff_wfc": 200,
        "cutoff_rho": 1600,
        "valence_electrons": 18.00,
        "total_magnetization": 0.00,
        "absolute_magnetization": 0.00,
        "md5": ""
    },
    "Ru": {
        "filename": "Ru_ONCV_PBEsol-1.0.upf",
        "total_psenergy": -187.92620536,
        "pseudopotential": "SG15",
        "relativistic": "scalar",
        "cutoff_wfc": 35,
        "cutoff_rho": 140,
        "valence_electrons": 16.00,
        "total_magnetization": 2.03,
        "absolute_magnetization": 2.95,
        "md5": ""
    },
    "Sb": {
        "filename": "sb_pbesol_v1.4.uspp.F.UPF",
        "total_psenergy": -184.25794536,
        "pseudopotential": "GBRV-1.4",
        "relativistic": "scalar",
        "cutoff_wfc": 55,
        "cutoff_rho": 440,
        "valence_electrons": 15.00,
        "total_magnetization": 0.01,
        "absolute_magnetization": 0.01,
        "md5": ""
    },
    "Sc": {
        "filename": "Sc.pbesol-spn-kjpaw_psl.0.2.3.UPF",
        "total_psenergy": -154.85505118,
        "pseudopotential": "031PAW",
        "relativistic": "scalar",
        "cutoff_wfc": 90,
        "cutoff_rho": 720,
        "valence_electrons": 11.00,
        "total_magnetization": 0.01,
        "absolute_magnetization": 0.85,
        "md5": ""
    },
    "Se": {
        "filename": "se_pbesol_v1.uspp.F.UPF",
        "total_psenergy": -43.02112211,
        "pseudopotential": "GBRV-1.2",
        "relativistic": "scalar",
        "cutoff_wfc": 30,
        "cutoff_rho": 240,
        "valence_electrons": 6.00,
        "total_magnetization": -0.00,
        "absolute_magnetization": 0.00,
        "md5": ""
    },
    "Si": {
        "filename": "Si.pbesol-n-rrkjus_psl.1.0.0.UPF",
        "total_psenergy": -10.91235831,
        "pseudopotential": "100US",
        "relativistic": "scalar",
        "cutoff_wfc": 30,
        "cutoff_rho": 240,
        "valence_electrons": 4.00,
        "total_magnetization": -0.00,
        "absolute_magnetization": 0.00,
        "md5": ""
    },
    "Sm": {
        "filename": "Sm.paw.z_16.atompaw.wentzcovitch.v1.2.upf",
        "total_psenergy": -596.58710044,
        "pseudopotential": "Wentzcovitch",
        "relativistic": "scalar",
        "cutoff_wfc": 40,
        "cutoff_rho": 320,
        "valence_electrons": 16.00,
        "total_magnetization": 0.02,
        "absolute_magnetization": 0.94,
        "md5": ""
    },
    "Sn": {
        "filename": "sn_pbesol_v1.4.uspp.F.UPF",
        "total_psenergy": -158.59772328,
        "pseudopotential": "GBRV-1.2",
        "relativistic": "scalar",
        "cutoff_wfc": 70,
        "cutoff_rho": 560,
        "valence_electrons": 14.00,
        "total_magnetization": -0.00,
        "absolute_magnetization": 0.00,
        "md5": ""
    },
    "S": {
        "filename": "s_pbesol_v1.4.uspp.F.UPF",
        "total_psenergy": -23.69322858,
        "pseudopotential": "GBRV-1.4",
        "relativistic": "scalar",
        "cutoff_wfc": 35,
        "cutoff_rho": 280,
        "valence_electrons": 6.00,
        "total_magnetization": 0.00,
        "absolute_magnetization": 0.00,
        "md5": ""
    },
    "Sr": {
        "filename": "sr_pbesol_v1.uspp.F.UPF",
        "total_psenergy": -70.03566071,
        "pseudopotential": "GBRV-1.2",
        "relativistic": "scalar",
        "cutoff_wfc": 40,
        "cutoff_rho": 320,
        "valence_electrons": 10.00,
        "total_magnetization": 0.00,
        "absolute_magnetization": 0.00,
        "md5": ""
    },
    "Ta": {
        "filename": "ta_pbesol_v1.uspp.F.UPF",
        "total_psenergy": -141.10196762,
        "pseudopotential": "GBRV-1.2",
        "relativistic": "scalar",
        "cutoff_wfc": 50,
        "cutoff_rho": 400,
        "valence_electrons": 13.00,
        "total_magnetization": 0.96,
        "absolute_magnetization": 2.47,
        "md5": ""
    },
    "Tb": {
        "filename": "Tb.paw.z_19.atompaw.wentzcovitch.v1.2.upf",
        "total_psenergy": -720.79592117,
        "pseudopotential": "Wentzcovitch",
        "relativistic": "scalar",
        "cutoff_wfc": 40,
        "cutoff_rho": 320,
        "valence_electrons": 19.00,
        "total_magnetization": -5.42,
        "absolute_magnetization": 5.45,
        "md5": ""
    },
    "Tc": {
        "filename": "Tc_ONCV_PBEsol-1.0.upf",
        "total_psenergy": -160.58076549,
        "pseudopotential": "SG15",
        "relativistic": "scalar",
        "cutoff_wfc": 40,
        "cutoff_rho": 160,
        "valence_electrons": 15.00,
        "total_magnetization": 1.11,
        "absolute_magnetization": 3.07,
        "md5": ""
    },
    "Te": {
        "filename": "Te.us.z_6.ld1.psl.v1.0.0-low.upf",
        "total_psenergy": -28.20818116,
        "pseudopotential": "US100-low",
        "relativistic": "scalar",
        "cutoff_wfc": 50,
        "cutoff_rho": 400,
        "valence_electrons": 6.00,
        "total_magnetization": -0.00,
        "absolute_magnetization": 0.02,
        "md5": ""
    },
    "Th": {
        "filename": "Th.paw.z_12.ld1.uni-marburg.v0.upf",
        "total_psenergy": -952.75732033,
        "pseudopotential": "MalteSachs",
        "relativistic": "scalar",
        "cutoff_wfc": 60,
        "cutoff_rho": 480,
        "valence_electrons": 12.00,
        "total_magnetization": 0.26,
        "absolute_magnetization": 1.78,
        "md5": ""
    },
    "Ti": {
        "filename": "ti_pbesol_v1.4.uspp.F.UPF",
        "total_psenergy": -118.72737987,
        "pseudopotential": "GBRV-1.4",
        "relativistic": "scalar",
        "cutoff_wfc": 40,
        "cutoff_rho": 320,
        "valence_electrons": 12.00,
        "total_magnetization": 0.01,
        "absolute_magnetization": 1.95,
        "md5": ""
    },
    "Tl": {
        "filename": "tl_pbesol_v1.2.uspp.F.UPF",
        "total_psenergy": -144.50909613,
        "pseudopotential": "GBRV-1.2",
        "relativistic": "scalar",
        "cutoff_wfc": 70,
        "cutoff_rho": 560,
        "valence_electrons": 13.00,
        "total_magnetization": -0.00,
        "absolute_magnetization": 0.01,
        "md5": ""
    },
    "Tm": {
        "filename": "Tm.paw.z_23.atompaw.wentzcovitch.v1.2.upf",
        "total_psenergy": -937.77550027,
        "pseudopotential": "Wentzcovitch",
        "relativistic": "scalar",
        "cutoff_wfc": 40,
        "cutoff_rho": 320,
        "valence_electrons": 23.00,
        "total_magnetization": 1.00,
        "absolute_magnetization": 1.02,
        "md5": ""
    },
    "U": {
        "filename": "U.paw.z_14.ld1.uni-marburg.v0.upf",
        "total_psenergy": -1014.51350607,
        "pseudopotential": "MalteSachs",
        "relativistic": "scalar",
        "cutoff_wfc": 60,
        "cutoff_rho": 480,
        "valence_electrons": 14.00,
        "total_magnetization": -0.41,
        "absolute_magnetization": 2.70,
        "md5": ""
    },
    "V": {
        "filename": "v_pbesol_v1.4.uspp.F.UPF",
        "total_psenergy": -144.47082518,
        "pseudopotential": "GBRV-1.4",
        "relativistic": "scalar",
        "cutoff_wfc": 40,
        "cutoff_rho": 320,
        "valence_electrons": 13.00,
        "total_magnetization": -0.95,
        "absolute_magnetization": 2.62,
        "md5": ""
    },
    "W": {
        "filename": "w_pbesol_v1.2.uspp.F.UPF",
        "total_psenergy": -158.26195334,
        "pseudopotential": "GBRV-1.2",
        "relativistic": "scalar",
        "cutoff_wfc": 50,
        "cutoff_rho": 400,
        "valence_electrons": 14.00,
        "total_magnetization": 0.55,
        "absolute_magnetization": 2.67,
        "md5": ""
    },
    "Xe": {
        "filename": "Xe.paw.z_18.ld1.psl.v1.0.0-high.upf",
        "total_psenergy": -587.26083411,
        "pseudopotential": "100PAW",
        "relativistic": "scalar",
        "cutoff_wfc": 150,
        "cutoff_rho": 900,
        "valence_electrons": 18.00,
        "total_magnetization": 0.00,
        "absolute_magnetization": 0.00,
        "md5": ""
    },
    "Yb": {
        "filename": "Yb.paw.z_24.atompaw.wentzcovitch.v1.2.upf",
        "total_psenergy": -1002.37701552,
        "pseudopotential": "Wentzcovitch",
        "relativistic": "scalar",
        "cutoff_wfc": 40,
        "cutoff_rho": 320,
        "valence_electrons": 24.00,
        "total_magnetization": -0.00,
        "absolute_magnetization": 0.00,
        "md5": ""
    },
    "Y": {
        "filename": "y_pbesol_v1.4.uspp.F.UPF",
        "total_psenergy": -92.39303528,
        "pseudopotential": "GBRV-1.2",
        "relativistic": "scalar",
        "cutoff_wfc": 35,
        "cutoff_rho": 280,
        "valence_electrons": 11.00,
        "total_magnetization": -0.01,
        "absolute_magnetization": 0.01,
        "md5": ""
    },
    "Zn": {
        "filename": "zn_pbesol_v1.uspp.F.UPF",
        "total_psenergy": -461.14167661,
        "pseudopotential": "GBRV-1.2",
        "relativistic": "scalar",
        "cutoff_wfc": 90,
        "cutoff_rho": 720,
        "valence_electrons": 20.00,
        "total_magnetization": 0.00,
        "absolute_magnetization": 0.00,
        "md5": ""
    },
    "Zr": {
        "filename": "zr_pbesol_v1.uspp.F.UPF",
        "total_psenergy": -98.64067176,
        "pseudopotential": "GBRV-1.2",
        "relativistic": "scalar",
        "cutoff_wfc": 30,
        "cutoff_rho": 240,
        "valence_electrons": 12.00,
        "total_magnetization": 0.00,
        "absolute_magnetization": 0.01,
        "md5": ""
    },
    "XX": {
        "filename": "",
        "total_psenergy": 0.0,
        "pseudopotential": "none",
        "relativistic": "none",
        "cutoff_wfc": 0.0,
        "cutoff_rho": 0.0,
        "valence_electrons": 0.0,
        "md5": ""
    }
}
