{
    "Er_mp-99_conventional_standard.cif":{
        "Final Energy/Atom": -4.5574,
        "C11":  85,
        "C12":  26,
        "C13":  23,
        "C22":  85,
        "C23":  23,
        "C33":  89,
        "C44":  28,
        "C55":  28,
        "C66":  30,
        "Bvrh": 44,
        "Gvrh": 30
    },
    "Er_mp-99_(1_0_-1_0).cif":{
        "Final Energy/Atom": -4.5574,
        "Surface Energy": 0.99
    },
    "Er_mp-99_5bc7fd5a5292202329623433.cif":{
        "Final Energy/Atom": -4.5574,
        "Grain Boundaries Energy": 0.32
    },
    "Er_mp-10752_conventional_standard.cif":{
        "Final Energy/Atom": -4.5408,
        "C11":  66,
        "C12":  31,
        "C13":  31,
        "C22":  66,
        "C23":  31,
        "C33":  66,
        "C44":  35,
        "C55":  35,
        "C66":  35,
        "Bvrh": 42,
        "Gvrh": 27
    },
    "Er_mp-10753_conventional_standard.cif":{
        "Final Energy/Atom": -4.4248,
        "C11":  23,
        "C12":  48,
        "C13":  48,
        "C22":  23,
        "C23":  48,
        "C33":  23,
        "C44":  24,
        "C55":  24,
        "C66":  24,
        "Bvrh": 40,
        "Gvrh":-65
    }
}
